geometricconvolutions/__init__.py
geometricconvolutions/data.py
geometricconvolutions/geometric.py
geometricconvolutions/ml.py
geometricconvolutions/models.py
geometricconvolutions/utils.py
geometricconvolutions-0.1.0.dist-info/LICENSE
geometricconvolutions-0.1.0.dist-info/METADATA
geometricconvolutions-0.1.0.dist-info/WHEEL
geometricconvolutions-0.1.0.dist-info/top_level.txt
geometricconvolutions-0.1.0.dist-info/RECORD
