Metadata-Version: 2.1
Name: geometricconvolutions
Version: 0.1.0
Summary: Package for building Convolutional Neural Networks on images of tensors.
Home-page: https://github.com/WilsonGregory/GeometricConvolutions
Author: Wilson Gregory, David Hogg
Author-email: wilson.g.gregory@gmail.com
Project-URL: Bug Tracker, https://github.com/WilsonGregory/GeometricConvolutions/issues
Classifier: Programming Language :: Python :: 3
Classifier: License :: OSI Approved :: MIT License
Classifier: Operating System :: OS Independent
Requires-Python: >=3.7
License-File: LICENSE
Requires-Dist: matplotlib
Requires-Dist: numpy
Requires-Dist: jax
Requires-Dist: cmastro
Requires-Dist: optax
Requires-Dist: imageio
